ssm_tool_test/__init__.py
ssm_tool_test/ssm.py
ssm_tool_test-3.0.0.dist-info/LICENSE
ssm_tool_test-3.0.0.dist-info/METADATA
ssm_tool_test-3.0.0.dist-info/WHEEL
ssm_tool_test-3.0.0.dist-info/top_level.txt
ssm_tool_test-3.0.0.dist-info/RECORD
