Metadata-Version: 2.1
Name: ssm-tool-test
Version: 3.0.0
Summary: A small example package to get ssm parameters from aws
Author-email: Roldan Author <jdroldan@playvox.com>
Project-URL: Homepage, https://github.com/pypa/sampleproject
Project-URL: Bug Tracker, https://github.com/pypa/sampleproject/issues
Classifier: Programming Language :: Python :: 3
Classifier: License :: OSI Approved :: MIT License
Classifier: Operating System :: OS Independent
Requires-Python: >=3.7
License-File: LICENSE
Requires-Dist: aiobotocore
